<?xml version="1.0" encoding="UTF-8"?>
<data>
	<node>
		<pid><![CDATA[338192]]></pid>
		<title><![CDATA[Flinders Street Railway Station, Melbourne]]></title>
		<description><![CDATA[Collection Of Postcard Views Of Melbourne Public Buildings Cards are printed in colour, with titles in red on face. -- 1. Commonwealth Parliament House -- 2. General Post Office -- 3. Government House -- 4. General Hospital -- 5. St. Paul's Cathedral -- 6. Public Library and Art Gallery -- 7. Fire Station, Easter]]></description>
		<identifier><![CDATA[pc004493]]></identifier>
		<format><![CDATA[image/jpg]]></format>
		<type><![CDATA[StillImage]]></type>
		<accessrightsstatement><![CDATA[No copyright restrictions apply.]]></accessrightsstatement>
		<copyrightstatement><![CDATA[This work is out of copyright]]></copyrightstatement>
		<relationship><![CDATA[Hoddles Grid App]]></relationship>
		<digitaluri><![CDATA[http://api.slv.vic.gov.au/access_record/338211]]></digitaluri>
		<ilmsidentifier><![CDATA[1913100]]></ilmsidentifier>
		<ilmsuri><![CDATA[http://search.slv.vic.gov.au/MAIN:Everything:SLV_VOYAGER1913100]]></ilmsuri>
		<creator2fcontributor><![CDATA[Cole, E. W. (Edward William), 1832-1918.]]></creator2fcontributor>
		<date><![CDATA[1902/1908]]></date>
		<location><![CDATA[]]></location>
		<accessionnumber><![CDATA[H2009.98/1]]></accessionnumber>
	</node>
</data>
